shape_areas/__init__.py
shape_areas/shape_areas.py
shape_areas/testshape_area.py
area_of_shapes-0.1.dist-info/LICENCE
area_of_shapes-0.1.dist-info/METADATA
area_of_shapes-0.1.dist-info/WHEEL
area_of_shapes-0.1.dist-info/top_level.txt
area_of_shapes-0.1.dist-info/RECORD
