Metadata-Version: 2.1
Name: area_of_shapes
Version: 0.1
Summary: A simple python package to calculate the area of different shapes
Home-page: https://github.com/amaechijude/area
Author: Amaechi Ugwu
Author-email: amaechijude178@gmail.com
Classifier: Programming Language :: Python :: 3
Classifier: License :: OSI Approved :: MIT License
Classifier: Operating System :: OS Independent
Requires-Python: >=3.6
License-File: LICENCE
